schedules_tools/__init__.py
schedules_tools/converter.py
schedules_tools/diff.py
schedules_tools/discovery.py
schedules_tools/jsondate.py
schedules_tools/models.py
schedules_tools/utils.py
schedules_tools/version.py
schedules_tools/batches/__init__.py
schedules_tools/batches/schedule_batch.py
schedules_tools/batches/utils.py
schedules_tools/batches/templates/example.yml
schedules_tools/schedule_handlers/__init__.py
schedules_tools/schedule_handlers/confluencehtml.py
schedules_tools/schedule_handlers/html.py
schedules_tools/schedule_handlers/ics.py
schedules_tools/schedule_handlers/jsonstruct.py
schedules_tools/schedule_handlers/msp.py
schedules_tools/schedule_handlers/rally.py
schedules_tools/schedule_handlers/smart_sheet.py
schedules_tools/storage_handlers/__init__.py
schedules_tools/storage_handlers/local.py
schedules_tools/tests/__init__.py
schedules_tools/tests/intermediary-struct-reference-duplicated-names.json
schedules_tools/tests/intermediary-struct-reference.json
schedules_tools/tests/test_check_tasks.py
schedules_tools/tests/test_convert.py
schedules_tools/tests/test_diff.py
schedules_tools/tests/test_handler_specifics.py
schedules_tools/tests/test_handlers.py
schedules_tools/tests/fixtures/schedule_diff/sched_diff_dates_changed.json
schedules_tools/tests/fixtures/schedule_diff/sched_diff_dates_changed.txt
schedules_tools/tests/fixtures/schedule_diff/sched_diff_flags_changed_trim_time.json
schedules_tools/tests/fixtures/schedule_diff/sched_diff_flags_changed_trim_time.txt
schedules_tools/tests/fixtures/schedule_diff/sched_diff_flags_changed_trim_time_compare_flags.json
schedules_tools/tests/fixtures/schedule_diff/sched_diff_flags_changed_trim_time_compare_flags.txt
schedules_tools/tests/fixtures/schedule_diff/sched_diff_reference_trim_time_compare_flags.json
schedules_tools/tests/fixtures/schedule_diff/sched_diff_reference_trim_time_compare_flags.txt
schedules_tools/tests/fixtures/schedule_diff/sched_diff_subtask_added.json
schedules_tools-8.16.1.dist-info/LICENSE.txt
schedules_tools-8.16.1.dist-info/METADATA
schedules_tools-8.16.1.dist-info/WHEEL
schedules_tools-8.16.1.dist-info/entry_points.txt
schedules_tools-8.16.1.dist-info/top_level.txt
schedules_tools-8.16.1.dist-info/RECORD
