Metadata-Version: 2.1
Name: schedules-tools
Version: 8.16.1
Summary: Schedules tools to handle/convert various schedule formats
Home-page: https://github.com/RedHat-Eng-PGM/python-schedules-tools
Author: RH PLM
Author-email: pp-dev-list@redhat.com
License: MIT
Project-URL: Bug Tracker, https://github.com/RedHat-Eng-PGM/python-schedules-tools/issues
Platform: UNKNOWN
Classifier: Programming Language :: Python :: 3
Classifier: Programming Language :: Python :: 3.6
Classifier: Programming Language :: Python :: 3.7
Classifier: Programming Language :: Python :: 3.8
Classifier: Programming Language :: Python :: 3.9
Classifier: License :: OSI Approved :: MIT License
Requires-Python: >=3.6
License-File: LICENSE.txt
Requires-Dist: icalendar
Requires-Dist: lxml
Requires-Dist: pyral (>=1.5)
Requires-Dist: python-dateutil
Requires-Dist: pytz
Requires-Dist: pyyaml
Requires-Dist: smartsheet-python-sdk-py39
